t2kdm/__init__.py
t2kdm/backends.py
t2kdm/cache.py
t2kdm/cli.py
t2kdm/commands.py
t2kdm/configuration.py
t2kdm/interactive.py
t2kdm/legacy_backends.py
t2kdm/maid.py
t2kdm/storage.py
t2kdm/tests.py
t2kdm/utils.py
t2kdm/version.py
t2kdm-1.17.6.dist-info/LICENSE
t2kdm-1.17.6.dist-info/METADATA
t2kdm-1.17.6.dist-info/WHEEL
t2kdm-1.17.6.dist-info/entry_points.txt
t2kdm-1.17.6.dist-info/top_level.txt
t2kdm-1.17.6.dist-info/zip-safe
t2kdm-1.17.6.dist-info/RECORD
