Metadata-Version: 2.1
Name: t2kdm
Version: 1.17.6
Summary: T2K Data Manager
Home-page: https://github.com/t2k-software/t2kdm
Author: Lukas Koch
Author-email: lukas.koch@mailbox.org
License: MIT
Classifier: Development Status :: 5 - Production/Stable
Classifier: Intended Audience :: Developers
Classifier: Intended Audience :: Science/Research
Classifier: Topic :: Scientific/Engineering
Classifier: License :: OSI Approved :: MIT License
Classifier: Programming Language :: Python :: 3.9
Requires-Python: >=3.6
License-File: LICENSE
Requires-Dist: sh >=1.12.14
Requires-Dist: six >=1.10.0
Requires-Dist: appdirs >=1.4.3
Requires-Dist: multiprocess >=0.70.8
